touchstone_auth/__init__.py
touchstone_auth/__main__.py
touchstone_auth/okta_parsing.py
touchstone_auth/sso.py
touchstone_auth-0.8.0.dist-info/LICENSE
touchstone_auth-0.8.0.dist-info/METADATA
touchstone_auth-0.8.0.dist-info/WHEEL
touchstone_auth-0.8.0.dist-info/top_level.txt
touchstone_auth-0.8.0.dist-info/RECORD
