Metadata-Version: 2.1
Name: touchstone-auth
Version: 0.8.0
Summary: Access Touchstone SSO sites without a web browser.
Home-page: https://github.com/meson800/touchstone-auth
Author: Christopher Johnstone
Author-email: meson800@gmail.com
Project-URL: Bug Tracker, https://github.com/meson800/touchstone-auth/issues
Classifier: Development Status :: 4 - Beta
Classifier: Programming Language :: Python :: 3
Classifier: License :: OSI Approved :: MIT License
Classifier: Operating System :: OS Independent
Classifier: Topic :: Internet :: WWW/HTTP :: Session
Requires-Python: >=3.6
License-File: LICENSE
Requires-Dist: beautifulsoup4
Requires-Dist: requests
Requires-Dist: requests-pkcs12 ==1.24
Requires-Dist: requests-kerberos
Requires-Dist: typing-extensions
